evarequests/__init__.py
evarequests/eva_requests.py
evarequests-1.0.0.dist-info/LICENSE
evarequests-1.0.0.dist-info/METADATA
evarequests-1.0.0.dist-info/WHEEL
evarequests-1.0.0.dist-info/top_level.txt
evarequests-1.0.0.dist-info/RECORD
