Metadata-Version: 2.1
Name: evarequests
Version: 1.0.0
Summary: Asynchronous HTTP Client for Python.
Home-page: https://github.com/shizhao-git/evarequests
Author: shizhao
Author-email: shizhao@mail.nwpu.edu.cn
License: UNKNOWN
Platform: UNKNOWN
License-File: LICENSE
Requires-Dist: requests
